{
    "PleasesigninbeforeanymovementintheCMV": "Please sign in before any movement in the CMV",
    "login": "Login",
    "userHOS": "UserHOS",
    "password": "Password",
    "latitude": "Latitude",
    "longitude": "Longitude",
    "Updatedon": "Updated on",
    "AlertSwithBluetooth1": "Dumax requires turning on Bluetooth",
    "AlertSwithBluetooth2": "and also requires connecting the application to your tracking device",
    "noAllow": "Don't allow",
    "turnOn": "Turn On",
    "connectingtodevice": "Connecting to device",
    "ConnecttoSelectedDevice": "Connect to Selected Device",
    "searchDevices": "Search Devices",
    "continue": "Continue",
    "warning": "Warning",
    "youdidnotselectanydevice": "You did not select any device",
    "cancel": "Cancel",
    "searchingDevices": "Searching Devices",
    "devicesECM": "Devices ECM",
    "hoursofservice": "Hours of Service",
    "Selectanupdate": "Select an update",
    "driverName": "Driver Name",
    "driverStatus": "Driver Status",
    "onDuty": "ON-DUTY",
    "driving": "DRIVING",
    "Sleeper": "SLEEPER",
    "passenger": "PASSENGER",
    "offDuty": "OFF-DUTY",
    "posibleViolation": "Posible Violation",
    "Menu": "Menu",
    "logBook": "Log Book",
    "diagnosis": "Diagnosis",
    "vehicleProfile": "Vehicle Profile",
    "violations": "Violations",
    "driverProfile": "Driver Profile",
    "aboutELD": "About ELD",
    "annotations": "Annotations",
    "certification": "Certification",
    "certifyLogs": "Certify Logs",
    "entryOfSecondDriver": "Entry of Second Driver",
    "notifications": "Notifications",
    "shipments": "Shipments",
    "searchingLogs": "Searching Logs",
    "logs": "Logs",
    "undefinedLogs": "Undefined Logs",
    "diagnosingUnit": "Diagnosing Unit",
    "test": "Test",
    "locationAvailability": "Location Availability",
    "storageSpace": "Storage Space",
    "batteryLevel": "Battery Level",
    "bluetoothConnectibility": "Bluetooth Connectibility",
    "engineData": "Engine Data",
    "odometer": "Odometer",
    "speed": "Speed",
    "engineHours": "Engine Hours",
    "truckNumber": "Truck Number",
    "truckVIN": "Truck VIN",
    "trailerNumber": "Trailer Number",
    "shippingDocumentNumber": "Shipping Document Number",
    "accumulatedMiles": "Accumulated Miles",
    "visualOdometer": "Visual Odometer",
    "save": "Save",
    "violationTittle": "Violation Tittle",
    "Name": "Name",
    "companyName": "Company Name",
    "companySchedule": "Company Schedule",
    "LicenseIssuanceStatus": "License Issuance Status",
    "licenseNumber": "License Number",
    "operationMode": "Operation Mode",
    "noAvailable": "No Available",
    "macAddress": "Mac Address",
    "FMCSAregistrationInformation": "FMCSA registration Information",
    "device": "Device",
    "modalIdentifier": "Modal Identifier",
    "registrationID": "Registration ID",
    "registeredWithFMCSA": "Registered with FMCSA",
    "certify": "Certify",
    "loading": "Loading",
    "incorrectUserOrPassword": "Incorrect user or password",
    "SelectaCarrier": "Select a Carrier",
    "thereIsnoDevicesAvailable": "There is no devices available",
    "StopMovementDetected": "Stop Movement Detected",
    "changeTo": "change to",
    "areYouSureYouWantTo": "Are you sure you want to",
    "confirm": "Confirm",
    "comment": "Comment",
    "ifyouWish": "If you wish",
    "youCanAddAComment": "you can add a comment",
    "unloading": "Unloading",
    "hooking": "Hooking",
    "dropping": "Dropping",
    "repairing": "Repairing",
    "DOTInspection": "DOT Inspection",
    "other": "Other",
    "observations": "Observations",
    "status": "Status",
    "sequenceIDNumber": "Sequence ID Number",
    "startTime": "Start Time",
    "finishTime": "Finish Time",
    "elapsedTime": "Elapsed Time",
    "location": "Location",
    "carrier": "Carrier",
    "certified": "Certified",
    "thereIsNoDataAvailable": "There is no data available",
    "exemptDriver": "Exempt Driver",
    "close": "close",
    "youAreNotAllowed": "You are not allowed to perform any action, please contact the administrator, reason: ",
    "recordStatus": "Record Status",
    "recordOrigin": "Record Origin",
    "type": "Type",
    "code": "Code",
    "accumulatedVehicleMiles": "Accumulated Vehicle Miles",
    "elapsedEngineHours": "Elapsed Engine Hours",
    "distanceSinceLastValidCoordinates": "Distance Since Last Valid Coordinates",
    "malfunctionIndicatorStatus": "Malfunction Indicator Status",
    "dataDiagnosticEventIndicatorStatus": "Data Diagnostic Event Indicator Status",
    "commentOrAnnotation": "Comment or Annotation",
    "driversLocationDescription": "Driver's Location Description",
    "dataCheckValue": "Data Check Value",
    "powerUnitNumber": "Power Unit Number",
    "Agree": "Agree",
    "NotReady": "Not Ready",
    "youCantCertify": "You cannot certify if there are no events during today. Please try again later.",
    "termsOfCertification": "“I hereby certify that my data entries and my record of duty status for this 24‐hour period are true and correct.”",
    "thereAreNoRecords": "There are no records available",
    "allRecordsAreCertified": "All records have been certified in the range of dates",
    "isNotAllowedanAdmin": "It is not allowed for an administrator user to log in, please contact support",
    "locationNotAvailable": "Location not available, please wait or try again later",
    "60minutesofinactivity": "60 minutes of inactivity",
    "eventDetails": "Event Details",
    "status:": "Status:",
    "home": "Home",
    "switchAccount": "Switch Account",
    "logout": "Logout",
    "AccountManagement": "Account Management",
    "userDriver": "Driver",
    "userCoDriver": "Codriver",
    "noLogoutAvailable": "No logout available, try closing all sesions",
    "kmAwayFrom": "km away from",
    "notAvailable": "Not Available",
    "closestLocation": "Closest Location",
    "assumeRecord": "assume the record",
    "assumedRecord": "Assumed Record",
    "city": "City",
    "state": "State",
    "address": "Address",
    "addTheRestOfTheInformation": "Add the rest of the information",
    "emptyFields": "Empty Fields",
    "distanceOnKM": "Distance on KM",
    "example": "Example",
    "addCommentToContinue": "Add a comment to continue with the editing",
    "selectArangeToContinue": "Select a range to continue with the certification",
    "pendingEventsToCertify": "Pending events to certify, certify now",
    "skip": "Skip",
    "advContinuePersonal": "You are in personal use. Do you want to continue using it?"
}